executor/executor/__init__.py
executor/executor/execsdk.py
executor/executor/processor.py
grebble_flow/__init__.py
grebble_flow/__main__.py
grebble_flow/helpers/__init__.py
grebble_flow/helpers/converter.py
grebble_flow/managment/__init__.py
grebble_flow/managment/executor.py
grebble_flow/managment/info.py
grebble_flow/managment/manager.py
grebble_flow/managment/processor.py
grebble_flow/processors/__init__.py
grebble_flow/processors/base.py
grebble_flow/processors/models.py
grebble_flow/processors/session.py
grebble_flow/transport/__init__.py
grebble_flow/transport/commands.py
grebble_flow/transport/manager.py
grebble_flow/transport/generated/__init__.py
grebble_flow/transport/generated/sdk/__init__.py
grebble_flow/transport/generated/sdk/v1/__init__.py
grebble_flow/transport/generated/sdk/v1/processor_pb2.py
grebble_flow/transport/generated/sdk/v1/processor_pb2_grpc.py
grebble_flow/transport/service/__init__.py
grebble_flow/transport/service/processor.py
grebble_flow/web/__init__.py
grebble_flow/web/managment.py
grebble_flow-0.0.3.52.dist-info/LICENSE
grebble_flow-0.0.3.52.dist-info/METADATA
grebble_flow-0.0.3.52.dist-info/WHEEL
grebble_flow-0.0.3.52.dist-info/top_level.txt
grebble_flow-0.0.3.52.dist-info/RECORD
