Metadata-Version: 2.1
Name: grebble-flow
Version: 0.0.3.52
Summary: Grebble flow
Home-page: https://github.com/Grebble-team/python-flow-helper
Author: Grebble
Author-email: info@grebble.io
License: UNKNOWN
Platform: UNKNOWN
License-File: LICENSE
Requires-Dist: click
Requires-Dist: grpcio
Requires-Dist: grpcio-tools
Requires-Dist: docstring-parser (==0.7.3)
Requires-Dist: dataclasses-json (==0.5.2)
